{
  "parent": "pizzacraft:root",
  "display": {
    "icon": {
      "item": "pizzacraft:mortar_and_pestle"
    },
    "title": {
      "translate": "advancements.pizzacraft.mortar_and_pestle.title"
    },
    "description": {
      "translate": "advancements.pizzacraft.mortar_and_pestle.description"
    },
    "frame": "task",
    "show_toast": false,
    "announce_to_chat": true,
    "hidden": false
  },
  "criteria": {
    "mortar_and_pestle": {
      "trigger": "minecraft:placed_block",
      "conditions": {
        "block": "pizzacraft:mortar_and_pestle"
      }
    }
  },
  "requirements": [
    [
      "mortar_and_pestle"
    ]
  ]
}